pyprql/__init__.py
pyprql/magic/README.md
pyprql/magic/__init__.py
pyprql/magic/prql.py
pyprql/pandas_accessor/__init__.py
pyprql/pandas_accessor/prql.py
pyprql/polars_namespace/__init__.py
pyprql/polars_namespace/prql.py
pyprql/py.typed
pyprql/tests/__init__.py
pyprql/tests/_regtest_outputs/test_magic.test_memory_db.out
pyprql/tests/_regtest_outputs/test_magic.test_pass_existing_engine.out
pyprql/tests/conftest.py
pyprql/tests/test_magic.py
pyprql/tests/test_polars_namespace.py
pyprql/tests/test_prql_python.py
pyprql-0.13.0.dist-info/LICENSE
pyprql-0.13.0.dist-info/METADATA
pyprql-0.13.0.dist-info/WHEEL
pyprql-0.13.0.dist-info/RECORD
