Metadata-Version: 2.3
Name: pyprql
Version: 0.13.0
Summary: Python extensions for PRQL
License: Apache-2.0
Author: Charlie Sanders
Author-email: charlie.fats@gmail.com
Requires-Python: >=3.10,<4.0
Classifier: License :: OSI Approved :: Apache Software License
Classifier: Programming Language :: Python
Classifier: Programming Language :: Python :: 3
Classifier: Programming Language :: Python :: 3.10
Classifier: Programming Language :: Python :: 3.11
Classifier: Programming Language :: Python :: 3.12
Classifier: Programming Language :: Python :: 3.13
Classifier: Programming Language :: Python :: 3.8
Classifier: Programming Language :: Python :: 3.9
Classifier: Typing :: Typed
Provides-Extra: polars
Requires-Dist: duckdb-engine (>=0.7,<0.16)
Requires-Dist: ipython (>=8.28.0,<9.0.0)
Requires-Dist: jupysql (>=0.10)
Requires-Dist: pandas (>=1.5)
Requires-Dist: polars (>=0.20.23) ; extra == "polars"
Requires-Dist: prqlc (>=0.13,<0.14)
Requires-Dist: traitlets (>=5)
Project-URL: Homepage, https://prql-lang.org
Project-URL: Repository, https://github.com/prql/pyprql
